README.md
setup.py
gantts/__init__.py
gantts/models.py
gantts/multistream.py
gantts/seqloss.py
gantts/version.py
gantts.egg-info/PKG-INFO
gantts.egg-info/SOURCES.txt
gantts.egg-info/dependency_links.txt
gantts.egg-info/requires.txt
gantts.egg-info/top_level.txt