Metadata-Version: 2.1
Name: gantts
Version: 0.1.0
Summary: PyTorch utils for GAN-based text-to-speech synthesis and voice conversion
Home-page: UNKNOWN
License: UNKNOWN
Platform: UNKNOWN
Provides-Extra: train
Provides-Extra: test
